vader_umpt/__init__.py
vader_umpt/vader/__init__.py
vader_umpt/vader/lexicons/booster.txt
vader_umpt/vader/lexicons/emoji_utf8_lexicon_ptbr.txt
vader_umpt/vader/lexicons/negate.txt
vader_umpt/vader/lexicons/vader_lexicon_ptbr.txt
vader_umpt/web.py
vader_umpt-0.1.2.dist-info/METADATA
vader_umpt-0.1.2.dist-info/WHEEL
vader_umpt-0.1.2.dist-info/entry_points.txt
vader_umpt-0.1.2.dist-info/RECORD
