Metadata-Version: 2.1
Name: vader-umpt
Version: 0.1.2
Summary: 
Author: Alexandre Flores
Author-email: pg50165@alunos.uminho.pt
Requires-Python: >=3.10,<4.0
Classifier: Programming Language :: Python :: 3
Classifier: Programming Language :: Python :: 3.10
Classifier: Programming Language :: Python :: 3.11
Requires-Dist: pandas (>=2.0.2,<3.0.0)
Requires-Dist: spacy (>=3.5.3,<4.0.0)
Requires-Dist: streamlit (>=1.23.1,<2.0.0)
Requires-Dist: typing-extensions (>=4.6.3,<5.0.0)
